pyegm/__init__.py
pyegm/pyegm.py
pyegm-0.3.0.dist-info/licenses/LICENSE
pyegm-0.3.0.dist-info/METADATA
pyegm-0.3.0.dist-info/WHEEL
pyegm-0.3.0.dist-info/top_level.txt
pyegm-0.3.0.dist-info/RECORD
