Metadata-Version: 2.4
Name: pyegm
Version: 0.3.0
Summary: PyEGM: a physics-inspired exemplar growth classifier with prototypes and arrival centers; NumPy/Scikit-Learn core GPU scoring is auto-enabled if the user installs PyTorch+CUDA separately.
Author-email: CJiangqiu <17787153839@qq.com>
License: MIT
Keywords: few-shot,FSCIL,class-incremental,long-tailed,prototype,arrival-centers,numpy,scikit-learn
Classifier: Development Status :: 4 - Beta
Classifier: Intended Audience :: Science/Research
Classifier: Topic :: Scientific/Engineering :: Artificial Intelligence
Classifier: License :: OSI Approved :: MIT License
Classifier: Programming Language :: Python :: 3
Classifier: Programming Language :: Python :: 3.8
Classifier: Programming Language :: Python :: 3.9
Classifier: Programming Language :: Python :: 3.10
Classifier: Programming Language :: Python :: 3.11
Classifier: Programming Language :: Python :: 3.12
Requires-Python: >=3.8
License-File: LICENSE
Requires-Dist: numpy>=1.21
Requires-Dist: scikit-learn>=1.0
Dynamic: license-file
